{
	"configurations" : 
	[
		{
			"directories" : 
			[
				{
					"build" : ".",
					"hasInstallRule" : true,
					"jsonFile" : "directory-.-Debug-d0570ff46f4de830c362.json",
					"minimumCMakeVersion" : 
					{
						"string" : "3.16"
					},
					"projectIndex" : 0,
					"source" : ".",
					"targetIndexes" : 
					[
						0,
						1,
						2
					]
				}
			],
			"name" : "Debug",
			"projects" : 
			[
				{
					"directoryIndexes" : 
					[
						0
					],
					"name" : "window",
					"targetIndexes" : 
					[
						0,
						1,
						2
					]
				}
			],
			"targets" : 
			[
				{
					"directoryIndex" : 0,
					"id" : "window::@6890427a1f51a3e7e1df",
					"jsonFile" : "target-window-Debug-6d7e5fad85b4155ea279.json",
					"name" : "window",
					"projectIndex" : 0
				},
				{
					"directoryIndex" : 0,
					"id" : "window_autogen::@6890427a1f51a3e7e1df",
					"jsonFile" : "target-window_autogen-Debug-86feb0f58e08b31628b7.json",
					"name" : "window_autogen",
					"projectIndex" : 0
				},
				{
					"directoryIndex" : 0,
					"id" : "window_autogen_timestamp_deps::@6890427a1f51a3e7e1df",
					"jsonFile" : "target-window_autogen_timestamp_deps-Debug-5927ada5c83437af1d43.json",
					"name" : "window_autogen_timestamp_deps",
					"projectIndex" : 0
				}
			]
		}
	],
	"kind" : "codemodel",
	"paths" : 
	{
		"build" : "/app/window/build/Desktop-Debug",
		"source" : "/app/window"
	},
	"version" : 
	{
		"major" : 2,
		"minor" : 6
	}
}
